ios_unittest_generator/__init__.py
ios_unittest_generator/__main__.py
ios_unittest_generator/build_file_utils.py
ios_unittest_generator/config.py
ios_unittest_generator/server.py
ios_unittest_generator/workflow_state.py
ios_unittest_generator/ios_test_patterns.json
ios_unittest_generator-4.19.4.dist-info/METADATA
ios_unittest_generator-4.19.4.dist-info/WHEEL
ios_unittest_generator-4.19.4.dist-info/entry_points.txt
ios_unittest_generator-4.19.4.dist-info/licenses/LICENSE
ios_unittest_generator-4.19.4.dist-info/RECORD
