Metadata-Version: 2.4
Name: ios_unittest_generator
Version: 4.19.4
Summary: MCP Server for generating iOS unit tests for Chromium/Edge projects
Author: Microsoft Edge iOS Team
License-Expression: BSD-3-Clause
License-File: LICENSE
Keywords: chromium,edge,ios,mcp,test-generation,unittest
Classifier: Development Status :: 4 - Beta
Classifier: Intended Audience :: Developers
Classifier: License :: OSI Approved :: BSD License
Classifier: Programming Language :: Python :: 3
Classifier: Programming Language :: Python :: 3.11
Classifier: Programming Language :: Python :: 3.12
Classifier: Topic :: Software Development :: Testing
Requires-Python: >=3.11
Requires-Dist: mcp<2.0.0,>=1.9.4
